{
    "title": "test bxl transfer",
    "cretPath": "../assets/cret.pem",
    "multiScene": true,
    "info": {
        "author": "覆盖物 + 帧动画 (scene3)"
    },
    "pano": {
        "fovTrans": true,
        "sceneTrans": true
    },
    "rotate": {
        "speed": 0.4,
        "start": 2000        
    },
    "sceneGroup": [{
        "id": "scene0",
        "name": "罗浮宫",
        "bxlPath": "../assets/scene0/scene0.bxl",
        "imgPath": "../assets/scene0/scene0.jpg",
        "thumbPath": "../assets/scene0/thumb0.jpg",
        "overlays": [{
            "id": "id1",
            "type": "dom",
            "actionType": "multiple",
            "content": "<a style='color:#e3b;'>进入场景2</a>",
            "sceneId": "scene1",
            "location": {
                "lng": 0,
                "lat": 0
            }
        }, {
            "id": "id2",
            "type": "dom",
            "actionType": "link",
            "content": "你好啊, baidu",
            "linkUrl": "http://www.baidu.com",
            "location": {
                "lng": 20,
                "lat": 30
            }
        }, {
            "id": "id3",
            "type": "mesh",
            "actionType": "link",
            "img": "../assets/chirst.jpg",
            "width": 50,
            "height": 50,
            "linkUrl": "http://www.baidu.com",
            "location": {
                "lng": 180,
                "lat": 0
            }
        }, {
            "id": "id4",
            "type": "dom",
            "actionType": "custom",
            "content": "custom button",
            "location": {
                "lng": -20,
                "lat": 10
            }
        }]
    }, {
        "id": "scene1",
        "name": "广角",
        "bxlPath": "../assets/scene1/scene1.bxl",
        "imgPath": "../assets/scene1/scene1.jpg",
        "thumbPath": "../assets/scene1/thumb1.jpg"
    }, {
        "id": "scene2",
        "name": "太极",
        "bxlPath": "../assets/scene2/scene2.bxl",
        "imgPath": "../assets/scene2/scene2.jpg",
        "thumbPath": "../assets/scene2/thumb2.jpg",
        "fov": 80,
        "overlays": [{
            "type": "animation",
            "category": "frame",
            "imgPath": "../assets/frames",
            "count": 11,
            "location": {
                "lng": 20,
                "lat": 25
            }
        }]  
    }, {
        "id": "scene3",
        "name": "暗夜",
        "fov": 100,
        "lng": 120,
        "lat": 90,
        "bxlPath": "../assets/scene3/scene3.bxl",
        "imgPath": "../assets/scene3/scene3.jpg",
        "thumbPath": "../assets/scene3/thumb3.jpg"
    }]
}